bws.py
clk_extension_bws-0.1.0.dist-info/entry_points.txt
clk_extension_bws-0.1.0.dist-info/licenses/LICENSE
clk_extension_bws-0.1.0.dist-info/WHEEL
clk_extension_bws-0.1.0.dist-info/METADATA
clk_extension_bws-0.1.0.dist-info/RECORD
