Metadata-Version: 2.4
Name: clk_extension_bws
Version: 0.1.0
Summary: A simple wrapper around bws
Author-email: Konubinix <konubinixweb@gmail.com>
License-Expression: MIT
License-File: LICENSE
Requires-Dist: clk
Project-URL: Home, https://github.com/clk-project/clk_extension_bws
